joshbasiccalculator/__init__.py
hashempackage-0.0.1.dist-info/LICENCE.txt
hashempackage-0.0.1.dist-info/METADATA
hashempackage-0.0.1.dist-info/WHEEL
hashempackage-0.0.1.dist-info/top_level.txt
hashempackage-0.0.1.dist-info/RECORD
