Metadata-Version: 2.1
Name: hashempackage
Version: 0.0.1
Summary: simple code hashem
Home-page: UNKNOWN
Author: Hashem Shaiban
Author-email: tvxx2043@gmail.com
License: MIT
Keywords: hashempackage
Platform: UNKNOWN
Classifier: Development Status :: 5 - Production/Stable
Classifier: Intended Audience :: Education
Classifier: Operating System :: Microsoft :: Windows :: Windows 10
Classifier: License :: OSI Approved :: MIT License
Classifier: Programming Language :: Python :: 3
License-File: LICENCE.txt
